zf_jenga-0.1.4.dist-info/METADATA
zf_jenga-0.1.4.dist-info/WHEEL
zf_jenga-0.1.4.dist-info/license_files/LICENSE
jenga/__init__.py
jenga/jenga.cpython-311-darwin.so
zf_jenga-0.1.4.dist-info/RECORD
